pyDIOPT/__init__.py
pyDIOPT/__version__.py
pyDIOPT/fetch.py
pyDIOPT/species.py
pyDIOPT/utils.py
pyDIOPT-0.1.2.dist-info/LICENSE
pyDIOPT-0.1.2.dist-info/METADATA
pyDIOPT-0.1.2.dist-info/WHEEL
pyDIOPT-0.1.2.dist-info/top_level.txt
pyDIOPT-0.1.2.dist-info/RECORD
